llm_trainer/__init__.py
llm_trainer/dataset/DataLoader.py
llm_trainer/dataset/__init__.py
llm_trainer/dataset/create_dataset.py
llm_trainer/evaluator/Evaluator.py
llm_trainer/evaluator/__init__.py
llm_trainer/trainer/LLMTrainer.py
llm_trainer/trainer/__init__.py
llm_trainer-1.0.4.dist-info/METADATA
llm_trainer-1.0.4.dist-info/WHEEL
llm_trainer-1.0.4.dist-info/RECORD
