Metadata-Version: 2.3
Name: llm-trainer
Version: 1.0.4
Summary: 🤖 Train your LLMs with ease and fun.
License: MIT
Author: Nikoláy Skripkó
Requires-Python: >=3.11
Classifier: License :: OSI Approved :: MIT License
Classifier: Programming Language :: Python :: 3
Classifier: Programming Language :: Python :: 3.11
Classifier: Programming Language :: Python :: 3.12
Classifier: Programming Language :: Python :: 3.13
Requires-Dist: accelerate (>=1.6.0,<2.0.0)
Requires-Dist: datasets (>=3.3.2,<4.0.0)
Requires-Dist: matplotlib (>=3.10.1,<4.0.0)
Requires-Dist: numpy (>=2.2.3,<3.0.0)
Requires-Dist: setuptools (>=78.1.0,<79.0.0)
Requires-Dist: tabulate (>=0.9.0,<0.10.0)
Requires-Dist: torch (>=2.6.0,<3.0.0)
Requires-Dist: tqdm (>=4.67.1,<5.0.0)
Requires-Dist: transformers (>=4.49.0,<5.0.0)
Project-URL: Repository, https://github.com/Skripkon/llm_trainer
